[
  {
    "datetime": "2023-04-13T00:00:00+00:00",
    "resolutioncode": "PT15M",
    "region": "Belgium",
    "measured": 0.0,
    "mostrecentforecast": 0.0,
    "mostrecentconfidence10": 0.0,
    "mostrecentconfidence90": 0.0,
    "dayahead11hforecast": 0.0,
    "dayahead11hconfidence10": 0.0,
    "dayahead11hconfidence90": 0.0,
    "dayaheadforecast": 0.0,
    "dayaheadconfidence10": 0.0,
    "dayaheadconfidence90": 0.0,
    "weekaheadforecast": 0.0,
    "weekaheadconfidence10": 0.0,
    "weekaheadconfidence90": 0.0,
    "monitoredcapacity": 7428.931,
    "loadfactor": 0.0
  },
  {
    "datetime": "2023-04-13T00:15:00+00:00",
    "resolutioncode": "PT15M",
    "region": "Belgium",
    "measured": 0.0,
    "mostrecentforecast": 0.0,
    "mostrecentconfidence10": 0.0,
    "mostrecentconfidence90": 0.0,
    "dayahead11hforecast": 0.0,
    "dayahead11hconfidence10": 0.0,
    "dayahead11hconfidence90": 0.0,
    "dayaheadforecast": 0.0,
    "dayaheadconfidence10": 0.0,
    "dayaheadconfidence90": 0.0,
    "weekaheadforecast": 0.0,
    "weekaheadconfidence10": 0.0,
    "weekaheadconfidence90": 0.0,
    "monitoredcapacity": 7428.931,
    "loadfactor": 0.0
  },
  {
    "datetime": "2023-04-13T00:30:00+00:00",
    "resolutioncode": "PT15M",
    "region": "Belgium",
    "measured": 0.0,
    "mostrecentforecast": 0.0,
    "mostrecentconfidence10": 0.0,
    "mostrecentconfidence90": 0.0,
    "dayahead11hforecast": 0.0,
    "dayahead11hconfidence10": 0.0,
    "dayahead11hconfidence90": 0.0,
    "dayaheadforecast": 0.0,
    "dayaheadconfidence10": 0.0,
    "dayaheadconfidence90": 0.0,
    "weekaheadforecast": 0.0,
    "weekaheadconfidence10": 0.0,
    "weekaheadconfidence90": 0.0,
    "monitoredcapacity": 7428.931,
    "loadfactor": 0.0
  },
  {
    "datetime": "2023-04-13T00:45:00+00:00",
    "resolutioncode": "PT15M",
    "region": "Belgium",
    "measured": 0.0,
    "mostrecentforecast": 0.0,
    "mostrecentconfidence10": 0.0,
    "mostrecentconfidence90": 0.0,
    "dayahead11hforecast": 0.0,
    "dayahead11hconfidence10": 0.0,
    "dayahead11hconfidence90": 0.0,
    "dayaheadforecast": 0.0,
    "dayaheadconfidence10": 0.0,
    "dayaheadconfidence90": 0.0,
    "weekaheadforecast": 0.0,
    "weekaheadconfidence10": 0.0,
    "weekaheadconfidence90": 0.0,
    "monitoredcapacity": 7428.931,
    "loadfactor": 0.0
  },
  {
    "datetime": "2023-04-13T01:00:00+00:00",
    "resolutioncode": "PT15M",
    "region": "Belgium",
    "measured": 0.0,
    "mostrecentforecast": 0.0,
    "mostrecentconfidence10": 0.0,
    "mostrecentconfidence90": 0.0,
    "dayahead11hforecast": 0.0,
    "dayahead11hconfidence10": 0.0,
    "dayahead11hconfidence90": 0.0,
    "dayaheadforecast": 0.0,
    "dayaheadconfidence10": 0.0,
    "dayaheadconfidence90": 0.0,
    "weekaheadforecast": 0.0,
    "weekaheadconfidence10": 0.0,
    "weekaheadconfidence90": 0.0,
    "monitoredcapacity": 7428.931,
    "loadfactor": 0.0
  },
  {
    "datetime": "2023-04-13T01:15:00+00:00",
    "resolutioncode": "PT15M",
    "region": "Belgium",
    "measured": 0.0,
    "mostrecentforecast": 0.0,
    "mostrecentconfidence10": 0.0,
    "mostrecentconfidence90": 0.0,
    "dayahead11hforecast": 0.0,
    "dayahead11hconfidence10": 0.0,
    "dayahead11hconfidence90": 0.0,
    "dayaheadforecast": 0.0,
    "dayaheadconfidence10": 0.0,
    "dayaheadconfidence90": 0.0,
    "weekaheadforecast": 0.0,
    "weekaheadconfidence10": 0.0,
    "weekaheadconfidence90": 0.0,
    "monitoredcapacity": 7428.931,
    "loadfactor": 0.0
  },
  {
    "datetime": "2023-04-13T01:30:00+00:00",
    "resolutioncode": "PT15M",
    "region": "Belgium",
    "measured": 0.0,
    "mostrecentforecast": 0.0,
    "mostrecentconfidence10": 0.0,
    "mostrecentconfidence90": 0.0,
    "dayahead11hforecast": 0.0,
    "dayahead11hconfidence10": 0.0,
    "dayahead11hconfidence90": 0.0,
    "dayaheadforecast": 0.0,
    "dayaheadconfidence10": 0.0,
    "dayaheadconfidence90": 0.0,
    "weekaheadforecast": 0.0,
    "weekaheadconfidence10": 0.0,
    "weekaheadconfidence90": 0.0,
    "monitoredcapacity": 7428.931,
    "loadfactor": 0.0
  },
  {
    "datetime": "2023-04-13T01:45:00+00:00",
    "resolutioncode": "PT15M",
    "region": "Belgium",
    "measured": 0.0,
    "mostrecentforecast": 0.0,
    "mostrecentconfidence10": 0.0,
    "mostrecentconfidence90": 0.0,
    "dayahead11hforecast": 0.0,
    "dayahead11hconfidence10": 0.0,
    "dayahead11hconfidence90": 0.0,
    "dayaheadforecast": 0.0,
    "dayaheadconfidence10": 0.0,
    "dayaheadconfidence90": 0.0,
    "weekaheadforecast": 0.0,
    "weekaheadconfidence10": 0.0,
    "weekaheadconfidence90": 0.0,
    "monitoredcapacity": 7428.931,
    "loadfactor": 0.0
  },
  {
    "datetime": "2023-04-13T02:00:00+00:00",
    "resolutioncode": "PT15M",
    "region": "Belgium",
    "measured": 0.0,
    "mostrecentforecast": 0.0,
    "mostrecentconfidence10": 0.0,
    "mostrecentconfidence90": 0.0,
    "dayahead11hforecast": 0.0,
    "dayahead11hconfidence10": 0.0,
    "dayahead11hconfidence90": 0.0,
    "dayaheadforecast": 0.0,
    "dayaheadconfidence10": 0.0,
    "dayaheadconfidence90": 0.0,
    "weekaheadforecast": 0.0,
    "weekaheadconfidence10": 0.0,
    "weekaheadconfidence90": 0.0,
    "monitoredcapacity": 7428.931,
    "loadfactor": 0.0
  },
  {
    "datetime": "2023-04-13T02:15:00+00:00",
    "resolutioncode": "PT15M",
    "region": "Belgium",
    "measured": 0.0,
    "mostrecentforecast": 0.0,
    "mostrecentconfidence10": 0.0,
    "mostrecentconfidence90": 0.0,
    "dayahead11hforecast": 0.0,
    "dayahead11hconfidence10": 0.0,
    "dayahead11hconfidence90": 0.0,
    "dayaheadforecast": 0.0,
    "dayaheadconfidence10": 0.0,
    "dayaheadconfidence90": 0.0,
    "weekaheadforecast": 0.0,
    "weekaheadconfidence10": 0.0,
    "weekaheadconfidence90": 0.0,
    "monitoredcapacity": 7428.931,
    "loadfactor": 0.0
  },
  {
    "datetime": "2023-04-13T02:30:00+00:00",
    "resolutioncode": "PT15M",
    "region": "Belgium",
    "measured": 0.0,
    "mostrecentforecast": 0.0,
    "mostrecentconfidence10": 0.0,
    "mostrecentconfidence90": 0.0,
    "dayahead11hforecast": 0.0,
    "dayahead11hconfidence10": 0.0,
    "dayahead11hconfidence90": 0.0,
    "dayaheadforecast": 0.0,
    "dayaheadconfidence10": 0.0,
    "dayaheadconfidence90": 0.0,
    "weekaheadforecast": 0.0,
    "weekaheadconfidence10": 0.0,
    "weekaheadconfidence90": 0.0,
    "monitoredcapacity": 7428.931,
    "loadfactor": 0.0
  },
  {
    "datetime": "2023-04-13T02:45:00+00:00",
    "resolutioncode": "PT15M",
    "region": "Belgium",
    "measured": 0.0,
    "mostrecentforecast": 0.0,
    "mostrecentconfidence10": 0.0,
    "mostrecentconfidence90": 0.0,
    "dayahead11hforecast": 0.0,
    "dayahead11hconfidence10": 0.0,
    "dayahead11hconfidence90": 0.0,
    "dayaheadforecast": 0.0,
    "dayaheadconfidence10": 0.0,
    "dayaheadconfidence90": 0.0,
    "weekaheadforecast": 0.0,
    "weekaheadconfidence10": 0.0,
    "weekaheadconfidence90": 0.0,
    "monitoredcapacity": 7428.931,
    "loadfactor": 0.0
  },
  {
    "datetime": "2023-04-13T03:00:00+00:00",
    "resolutioncode": "PT15M",
    "region": "Belgium",
    "measured": 0.0,
    "mostrecentforecast": 0.0,
    "mostrecentconfidence10": 0.0,
    "mostrecentconfidence90": 0.0,
    "dayahead11hforecast": 0.0,
    "dayahead11hconfidence10": 0.0,
    "dayahead11hconfidence90": 0.0,
    "dayaheadforecast": 0.0,
    "dayaheadconfidence10": 0.0,
    "dayaheadconfidence90": 0.0,
    "weekaheadforecast": 0.0,
    "weekaheadconfidence10": 0.0,
    "weekaheadconfidence90": 0.0,
    "monitoredcapacity": 7428.931,
    "loadfactor": 0.0
  },
  {
    "datetime": "2023-04-13T03:15:00+00:00",
    "resolutioncode": "PT15M",
    "region": "Belgium",
    "measured": 0.0,
    "mostrecentforecast": 0.0,
    "mostrecentconfidence10": 0.0,
    "mostrecentconfidence90": 0.0,
    "dayahead11hforecast": 0.0,
    "dayahead11hconfidence10": 0.0,
    "dayahead11hconfidence90": 0.0,
    "dayaheadforecast": 0.0,
    "dayaheadconfidence10": 0.0,
    "dayaheadconfidence90": 0.0,
    "weekaheadforecast": 0.0,
    "weekaheadconfidence10": 0.0,
    "weekaheadconfidence90": 0.0,
    "monitoredcapacity": 7428.931,
    "loadfactor": 0.0
  },
  {
    "datetime": "2023-04-13T03:30:00+00:00",
    "resolutioncode": "PT15M",
    "region": "Belgium",
    "measured": 0.0,
    "mostrecentforecast": 0.0,
    "mostrecentconfidence10": 0.0,
    "mostrecentconfidence90": 0.0,
    "dayahead11hforecast": 0.0,
    "dayahead11hconfidence10": 0.0,
    "dayahead11hconfidence90": 0.0,
    "dayaheadforecast": 0.0,
    "dayaheadconfidence10": 0.0,
    "dayaheadconfidence90": 0.0,
    "weekaheadforecast": 0.0,
    "weekaheadconfidence10": 0.0,
    "weekaheadconfidence90": 0.0,
    "monitoredcapacity": 7428.931,
    "loadfactor": 0.0
  },
  {
    "datetime": "2023-04-13T03:45:00+00:00",
    "resolutioncode": "PT15M",
    "region": "Belgium",
    "measured": 0.0,
    "mostrecentforecast": 0.0,
    "mostrecentconfidence10": 0.0,
    "mostrecentconfidence90": 0.0,
    "dayahead11hforecast": 0.0,
    "dayahead11hconfidence10": 0.0,
    "dayahead11hconfidence90": 0.0,
    "dayaheadforecast": 0.0,
    "dayaheadconfidence10": 0.0,
    "dayaheadconfidence90": 0.0,
    "weekaheadforecast": 0.0,
    "weekaheadconfidence10": 0.0,
    "weekaheadconfidence90": 0.0,
    "monitoredcapacity": 7428.931,
    "loadfactor": 0.0
  },
  {
    "datetime": "2023-04-13T04:00:00+00:00",
    "resolutioncode": "PT15M",
    "region": "Belgium",
    "measured": 0.0,
    "mostrecentforecast": 0.0,
    "mostrecentconfidence10": 0.0,
    "mostrecentconfidence90": 0.0,
    "dayahead11hforecast": 0.0,
    "dayahead11hconfidence10": 0.0,
    "dayahead11hconfidence90": 0.0,
    "dayaheadforecast": 0.0,
    "dayaheadconfidence10": 0.0,
    "dayaheadconfidence90": 0.0,
    "weekaheadforecast": 0.0,
    "weekaheadconfidence10": 0.0,
    "weekaheadconfidence90": 0.0,
    "monitoredcapacity": 7428.931,
    "loadfactor": 0.0
  },
  {
    "datetime": "2023-04-13T04:15:00+00:00",
    "resolutioncode": "PT15M",
    "region": "Belgium",
    "measured": 0.0,
    "mostrecentforecast": 0.0,
    "mostrecentconfidence10": 0.0,
    "mostrecentconfidence90": 0.0,
    "dayahead11hforecast": 0.0,
    "dayahead11hconfidence10": 0.0,
    "dayahead11hconfidence90": 0.0,
    "dayaheadforecast": 0.0,
    "dayaheadconfidence10": 0.0,
    "dayaheadconfidence90": 0.0,
    "weekaheadforecast": 0.0,
    "weekaheadconfidence10": 0.0,
    "weekaheadconfidence90": 0.0,
    "monitoredcapacity": 7428.931,
    "loadfactor": 0.0
  },
  {
    "datetime": "2023-04-13T04:30:00+00:00",
    "resolutioncode": "PT15M",
    "region": "Belgium",
    "measured": 0.0,
    "mostrecentforecast": 0.0,
    "mostrecentconfidence10": 0.0,
    "mostrecentconfidence90": 0.0,
    "dayahead11hforecast": 0.0,
    "dayahead11hconfidence10": 0.0,
    "dayahead11hconfidence90": 0.0,
    "dayaheadforecast": 0.0,
    "dayaheadconfidence10": 0.0,
    "dayaheadconfidence90": 0.0,
    "weekaheadforecast": 0.0,
    "weekaheadconfidence10": 0.0,
    "weekaheadconfidence90": 0.0,
    "monitoredcapacity": 7428.931,
    "loadfactor": 0.0
  },
  {
    "datetime": "2023-04-13T04:45:00+00:00",
    "resolutioncode": "PT15M",
    "region": "Belgium",
    "measured": 0.0,
    "mostrecentforecast": 2.951,
    "mostrecentconfidence10": 1.872,
    "mostrecentconfidence90": 5.822,
    "dayahead11hforecast": 2.847,
    "dayahead11hconfidence10": 2.068,
    "dayahead11hconfidence90": 5.697,
    "dayaheadforecast": 2.91,
    "dayaheadconfidence10": 1.844,
    "dayaheadconfidence90": 7.589,
    "weekaheadforecast": 2.983,
    "weekaheadconfidence10": 2.712,
    "weekaheadconfidence90": 6.866,
    "monitoredcapacity": 7428.931,
    "loadfactor": 0.0
  },
  {
    "datetime": "2023-04-13T05:00:00+00:00",
    "resolutioncode": "PT15M",
    "region": "Belgium",
    "measured": 35.018,
    "mostrecentforecast": 33.747,
    "mostrecentconfidence10": 21.668,
    "mostrecentconfidence90": 71.874,
    "dayahead11hforecast": 34.448,
    "dayahead11hconfidence10": 25.661,
    "dayahead11hconfidence90": 67.476,
    "dayaheadforecast": 34.866,
    "dayaheadconfidence10": 21.11,
    "dayaheadconfidence90": 74.876,
    "weekaheadforecast": 31.122,
    "weekaheadconfidence10": 26.482,
    "weekaheadconfidence90": 54.018,
    "monitoredcapacity": 7428.931,
    "loadfactor": 0.471
  },
  {
    "datetime": "2023-04-13T05:15:00+00:00",
    "resolutioncode": "PT15M",
    "region": "Belgium",
    "measured": 115.841,
    "mostrecentforecast": 98.82,
    "mostrecentconfidence10": 64.562,
    "mostrecentconfidence90": 205.885,
    "dayahead11hforecast": 99.678,
    "dayahead11hconfidence10": 74.916,
    "dayahead11hconfidence90": 192.03,
    "dayaheadforecast": 100.164,
    "dayaheadconfidence10": 61.869,
    "dayaheadconfidence90": 204.221,
    "weekaheadforecast": 87.934,
    "weekaheadconfidence10": 69.503,
    "weekaheadconfidence90": 127.408,
    "monitoredcapacity": 7428.931,
    "loadfactor": 1.559
  },
  {
    "datetime": "2023-04-13T05:30:00+00:00",
    "resolutioncode": "PT15M",
    "region": "Belgium",
    "measured": 207.646,
    "mostrecentforecast": 185.426,
    "mostrecentconfidence10": 125.911,
    "mostrecentconfidence90": 370.196,
    "dayahead11hforecast": 185.453,
    "dayahead11hconfidence10": 143.706,
    "dayahead11hconfidence90": 344.918,
    "dayaheadforecast": 185.62,
    "dayaheadconfidence10": 115.193,
    "dayaheadconfidence90": 358.408,
    "weekaheadforecast": 156.721,
    "weekaheadconfidence10": 120.587,
    "weekaheadconfidence90": 216.562,
    "monitoredcapacity": 7428.931,
    "loadfactor": 2.795
  },
  {
    "datetime": "2023-04-13T05:45:00+00:00",
    "resolutioncode": "PT15M",
    "region": "Belgium",
    "measured": 338.818,
    "mostrecentforecast": 314.663,
    "mostrecentconfidence10": 212.228,
    "mostrecentconfidence90": 568.36,
    "dayahead11hforecast": 314.737,
    "dayahead11hconfidence10": 242.665,
    "dayahead11hconfidence90": 528.164,
    "dayaheadforecast": 315.058,
    "dayaheadconfidence10": 183.943,
    "dayaheadconfidence90": 542.557,
    "weekaheadforecast": 242.269,
    "weekaheadconfidence10": 201.774,
    "weekaheadconfidence90": 357.469,
    "monitoredcapacity": 7428.931,
    "loadfactor": 4.561
  },
  {
    "datetime": "2023-04-13T06:00:00+00:00",
    "resolutioncode": "PT15M",
    "region": "Belgium",
    "measured": 533.013,
    "mostrecentforecast": 505.002,
    "mostrecentconfidence10": 333.458,
    "mostrecentconfidence90": 775.619,
    "dayahead11hforecast": 482.599,
    "dayahead11hconfidence10": 377.14,
    "dayahead11hconfidence90": 729.297,
    "dayaheadforecast": 484.714,
    "dayaheadconfidence10": 267.499,
    "dayaheadconfidence90": 752.41,
    "weekaheadforecast": 353.918,
    "weekaheadconfidence10": 315.455,
    "weekaheadconfidence90": 547.152,
    "monitoredcapacity": 7428.931,
    "loadfactor": 7.175
  },
  {
    "datetime": "2023-04-13T06:15:00+00:00",
    "resolutioncode": "PT15M",
    "region": "Belgium",
    "measured": 734.646,
    "mostrecentforecast": 683.959,
    "mostrecentconfidence10": 446.276,
    "mostrecentconfidence90": 966.794,
    "dayahead11hforecast": 668.507,
    "dayahead11hconfidence10": 522.49,
    "dayahead11hconfidence90": 943.448,
    "dayaheadforecast": 672.492,
    "dayaheadconfidence10": 360.276,
    "dayaheadconfidence90": 977.041,
    "weekaheadforecast": 491.327,
    "weekaheadconfidence10": 429.084,
    "weekaheadconfidence90": 791.549,
    "monitoredcapacity": 7428.931,
    "loadfactor": 9.889
  },
  {
    "datetime": "2023-04-13T06:30:00+00:00",
    "resolutioncode": "PT15M",
    "region": "Belgium",
    "measured": 933.302,
    "mostrecentforecast": 874.896,
    "mostrecentconfidence10": 595.357,
    "mostrecentconfidence90": 1167.576,
    "dayahead11hforecast": 877.714,
    "dayahead11hconfidence10": 699.779,
    "dayahead11hconfidence90": 1176.858,
    "dayaheadforecast": 877.124,
    "dayaheadconfidence10": 496.979,
    "dayaheadconfidence90": 1218.608,
    "weekaheadforecast": 643.095,
    "weekaheadconfidence10": 537.416,
    "weekaheadconfidence90": 1078.456,
    "monitoredcapacity": 7428.931,
    "loadfactor": 12.563
  },
  {
    "datetime": "2023-04-13T06:45:00+00:00",
    "resolutioncode": "PT15M",
    "region": "Belgium",
    "measured": 1193.217,
    "mostrecentforecast": 1074.652,
    "mostrecentconfidence10": 752.934,
    "mostrecentconfidence90": 1389.938,
    "dayahead11hforecast": 1106.733,
    "dayahead11hconfidence10": 912.57,
    "dayahead11hconfidence90": 1415.03,
    "dayaheadforecast": 1091.703,
    "dayaheadconfidence10": 676.659,
    "dayaheadconfidence90": 1467.69,
    "weekaheadforecast": 801.436,
    "weekaheadconfidence10": 638.856,
    "weekaheadconfidence90": 1380.271,
    "monitoredcapacity": 7428.931,
    "loadfactor": 16.062
  },
  {
    "datetime": "2023-04-13T07:00:00+00:00",
    "resolutioncode": "PT15M",
    "region": "Belgium",
    "measured": 1413.788,
    "mostrecentforecast": 1321.069,
    "mostrecentconfidence10": 938.397,
    "mostrecentconfidence90": 1678.946,
    "dayahead11hforecast": 1342.249,
    "dayahead11hconfidence10": 1125.244,
    "dayahead11hconfidence90": 1656.754,
    "dayaheadforecast": 1306.272,
    "dayaheadconfidence10": 842.164,
    "dayaheadconfidence90": 1718.425,
    "weekaheadforecast": 967.397,
    "weekaheadconfidence10": 733.214,
    "weekaheadconfidence90": 1678.526,
    "monitoredcapacity": 7428.931,
    "loadfactor": 19.031
  },
  {
    "datetime": "2023-04-13T07:15:00+00:00",
    "resolutioncode": "PT15M",
    "region": "Belgium",
    "measured": 1602.879,
    "mostrecentforecast": 1520.876,
    "mostrecentconfidence10": 1067.976,
    "mostrecentconfidence90": 1939.707,
    "dayahead11hforecast": 1577.537,
    "dayahead11hconfidence10": 1310.996,
    "dayahead11hconfidence90": 1927.721,
    "dayaheadforecast": 1515.146,
    "dayaheadconfidence10": 977.699,
    "dayaheadconfidence90": 1980.2,
    "weekaheadforecast": 1139.512,
    "weekaheadconfidence10": 812.197,
    "weekaheadconfidence90": 1986.528,
    "monitoredcapacity": 7428.931,
    "loadfactor": 21.576
  },
  {
    "datetime": "2023-04-13T07:30:00+00:00",
    "resolutioncode": "PT15M",
    "region": "Belgium",
    "measured": 1842.402,
    "mostrecentforecast": 1717.109,
    "mostrecentconfidence10": 1226.173,
    "mostrecentconfidence90": 2174.103,
    "dayahead11hforecast": 1805.103,
    "dayahead11hconfidence10": 1493.268,
    "dayahead11hconfidence90": 2161.595,
    "dayaheadforecast": 1722.894,
    "dayaheadconfidence10": 1162.585,
    "dayaheadconfidence90": 2239.942,
    "weekaheadforecast": 1311.895,
    "weekaheadconfidence10": 889.77,
    "weekaheadconfidence90": 2274.125,
    "monitoredcapacity": 7428.931,
    "loadfactor": 24.8
  },
  {
    "datetime": "2023-04-13T07:45:00+00:00",
    "resolutioncode": "PT15M",
    "region": "Belgium",
    "measured": 1980.668,
    "mostrecentforecast": 1907.768,
    "mostrecentconfidence10": 1407.148,
    "mostrecentconfidence90": 2371.367,
    "dayahead11hforecast": 2029.64,
    "dayahead11hconfidence10": 1697.362,
    "dayahead11hconfidence90": 2365.518,
    "dayaheadforecast": 1937.032,
    "dayaheadconfidence10": 1397.083,
    "dayaheadconfidence90": 2472.391,
    "weekaheadforecast": 1477.957,
    "weekaheadconfidence10": 971.024,
    "weekaheadconfidence90": 2510.436,
    "monitoredcapacity": 7428.931,
    "loadfactor": 26.662
  },
  {
    "datetime": "2023-04-13T08:00:00+00:00",
    "resolutioncode": "PT15M",
    "region": "Belgium",
    "measured": 2023.899,
    "mostrecentforecast": 2194.59,
    "mostrecentconfidence10": 1671.896,
    "mostrecentconfidence90": 2562.275,
    "dayahead11hforecast": 2260.067,
    "dayahead11hconfidence10": 1876.777,
    "dayahead11hconfidence90": 2600.963,
    "dayaheadforecast": 2156.67,
    "dayaheadconfidence10": 1620.314,
    "dayaheadconfidence90": 2705.198,
    "weekaheadforecast": 1635.284,
    "weekaheadconfidence10": 1042.843,
    "weekaheadconfidence90": 2718.467,
    "monitoredcapacity": 7428.931,
    "loadfactor": 27.243
  },
  {
    "datetime": "2023-04-13T08:15:00+00:00",
    "resolutioncode": "PT15M",
    "region": "Belgium",
    "measured": 2017.161,
    "mostrecentforecast": 2393.129,
    "mostrecentconfidence10": 1790.598,
    "mostrecentconfidence90": 2801.533,
    "dayahead11hforecast": 2498.381,
    "dayahead11hconfidence10": 2003.48,
    "dayahead11hconfidence90": 2851.223,
    "dayaheadforecast": 2382.556,
    "dayaheadconfidence10": 1818.797,
    "dayaheadconfidence90": 2969.205,
    "weekaheadforecast": 1782.936,
    "weekaheadconfidence10": 1110.55,
    "weekaheadconfidence90": 2902.409,
    "monitoredcapacity": 7428.931,
    "loadfactor": 27.153
  },
  {
    "datetime": "2023-04-13T08:30:00+00:00",
    "resolutioncode": "PT15M",
    "region": "Belgium",
    "measured": 2154.632,
    "mostrecentforecast": 2604.321,
    "mostrecentconfidence10": 1939.131,
    "mostrecentconfidence90": 3048.338,
    "dayahead11hforecast": 2737.421,
    "dayahead11hconfidence10": 2152.033,
    "dayahead11hconfidence90": 3108.038,
    "dayaheadforecast": 2604.026,
    "dayaheadconfidence10": 2013.585,
    "dayaheadconfidence90": 3231.853,
    "weekaheadforecast": 1929.44,
    "weekaheadconfidence10": 1188.708,
    "weekaheadconfidence90": 3060.803,
    "monitoredcapacity": 7428.931,
    "loadfactor": 29.003
  },
  {
    "datetime": "2023-04-13T08:45:00+00:00",
    "resolutioncode": "PT15M",
    "region": "Belgium",
    "measured": 2400.356,
    "mostrecentforecast": 2833.893,
    "mostrecentconfidence10": 2122.334,
    "mostrecentconfidence90": 3269.509,
    "dayahead11hforecast": 2966.136,
    "dayahead11hconfidence10": 2341.596,
    "dayahead11hconfidence90": 3354.466,
    "dayaheadforecast": 2816.319,
    "dayaheadconfidence10": 2205.261,
    "dayaheadconfidence90": 3464.701,
    "weekaheadforecast": 2074.996,
    "weekaheadconfidence10": 1276.523,
    "weekaheadconfidence90": 3201.053,
    "monitoredcapacity": 7428.931,
    "loadfactor": 32.311
  },
  {
    "datetime": "2023-04-13T09:00:00+00:00",
    "resolutioncode": "PT15M",
    "region": "Belgium",
    "measured": 2244.163,
    "mostrecentforecast": 2683.516,
    "mostrecentconfidence10": 1826.604,
    "mostrecentconfidence90": 3293.691,
    "dayahead11hforecast": 3184.551,
    "dayahead11hconfidence10": 2481.837,
    "dayahead11hconfidence90": 3620.923,
    "dayaheadforecast": 3026.127,
    "dayaheadconfidence10": 2345.987,
    "dayaheadconfidence90": 3726.594,
    "weekaheadforecast": 2214.197,
    "weekaheadconfidence10": 1356.179,
    "weekaheadconfidence90": 3328.976,
    "monitoredcapacity": 7428.931,
    "loadfactor": 30.208
  },
  {
    "datetime": "2023-04-13T09:15:00+00:00",
    "resolutioncode": "PT15M",
    "region": "Belgium",
    "measured": 2527.26,
    "mostrecentforecast": 2912.397,
    "mostrecentconfidence10": 1963.321,
    "mostrecentconfidence90": 3609.263,
    "dayahead11hforecast": 3391.952,
    "dayahead11hconfidence10": 2556.058,
    "dayahead11hconfidence90": 3913.274,
    "dayaheadforecast": 3227.524,
    "dayaheadconfidence10": 2418.343,
    "dayaheadconfidence90": 4006.179,
    "weekaheadforecast": 2347.222,
    "weekaheadconfidence10": 1426.415,
    "weekaheadconfidence90": 3449.397,
    "monitoredcapacity": 7428.931,
    "loadfactor": 34.019
  },
  {
    "datetime": "2023-04-13T09:30:00+00:00",
    "resolutioncode": "PT15M",
    "region": "Belgium",
    "measured": 3035.28,
    "mostrecentforecast": 3144.908,
    "mostrecentconfidence10": 2149.312,
    "mostrecentconfidence90": 3873.57,
    "dayahead11hforecast": 3590.503,
    "dayahead11hconfidence10": 2666.331,
    "dayahead11hconfidence90": 4172.336,
    "dayaheadforecast": 3425.32,
    "dayaheadconfidence10": 2524.366,
    "dayaheadconfidence90": 4266.553,
    "weekaheadforecast": 2472.365,
    "weekaheadconfidence10": 1502.328,
    "weekaheadconfidence90": 3519.398,
    "monitoredcapacity": 7428.931,
    "loadfactor": 40.858
  },
  {
    "datetime": "2023-04-13T09:45:00+00:00",
    "resolutioncode": "PT15M",
    "region": "Belgium",
    "measured": 3233.843,
    "mostrecentforecast": 3374.653,
    "mostrecentconfidence10": 2375.318,
    "mostrecentconfidence90": 4069.268,
    "dayahead11hforecast": 3786.318,
    "dayahead11hconfidence10": 2832.654,
    "dayahead11hconfidence90": 4380.125,
    "dayaheadforecast": 3628.193,
    "dayaheadconfidence10": 2702.318,
    "dayaheadconfidence90": 4484.807,
    "weekaheadforecast": 2588.155,
    "weekaheadconfidence10": 1581.604,
    "weekaheadconfidence90": 3543.816,
    "monitoredcapacity": 7428.931,
    "loadfactor": 43.53
  },
  {
    "datetime": "2023-04-13T10:00:00+00:00",
    "resolutioncode": "PT15M",
    "region": "Belgium",
    "measured": 3496.77,
    "mostrecentforecast": 3248.017,
    "mostrecentconfidence10": 2157.326,
    "mostrecentconfidence90": 3928.979,
    "dayahead11hforecast": 3972.096,
    "dayahead11hconfidence10": 2988.488,
    "dayahead11hconfidence90": 4603.596,
    "dayaheadforecast": 3825.13,
    "dayaheadconfidence10": 2862.932,
    "dayaheadconfidence90": 4691.755,
    "weekaheadforecast": 2694.108,
    "weekaheadconfidence10": 1635.886,
    "weekaheadconfidence90": 3588.535,
    "monitoredcapacity": 7428.931,
    "loadfactor": 47.07
  },
  {
    "datetime": "2023-04-13T10:15:00+00:00",
    "resolutioncode": "PT15M",
    "region": "Belgium",
    "measured": 3582.995,
    "mostrecentforecast": 3457.945,
    "mostrecentconfidence10": 2202.583,
    "mostrecentconfidence90": 4129.068,
    "dayahead11hforecast": 4137.303,
    "dayahead11hconfidence10": 3103.362,
    "dayahead11hconfidence90": 4827.259,
    "dayaheadforecast": 4004.415,
    "dayaheadconfidence10": 2995.257,
    "dayaheadconfidence90": 4883.266,
    "weekaheadforecast": 2790.353,
    "weekaheadconfidence10": 1669.453,
    "weekaheadconfidence90": 3671.534,
    "monitoredcapacity": 7428.931,
    "loadfactor": 48.23
  },
  {
    "datetime": "2023-04-13T10:30:00+00:00",
    "resolutioncode": "PT15M",
    "region": "Belgium",
    "measured": 3969.118,
    "mostrecentforecast": 3631.382,
    "mostrecentconfidence10": 2297.292,
    "mostrecentconfidence90": 4289.6,
    "dayahead11hforecast": 4260.551,
    "dayahead11hconfidence10": 3193.332,
    "dayahead11hconfidence90": 4997.453,
    "dayaheadforecast": 4145.761,
    "dayaheadconfidence10": 3129.568,
    "dayaheadconfidence90": 5015.659,
    "weekaheadforecast": 2873.144,
    "weekaheadconfidence10": 1707.438,
    "weekaheadconfidence90": 3730.017,
    "monitoredcapacity": 7428.931,
    "loadfactor": 53.428
  },
  {
    "datetime": "2023-04-13T10:45:00+00:00",
    "resolutioncode": "PT15M",
    "region": "Belgium",
    "measured": 4073.221,
    "mostrecentforecast": 3769.319,
    "mostrecentconfidence10": 2442.657,
    "mostrecentconfidence90": 4404.505,
    "dayahead11hforecast": 4340.536,
    "dayahead11hconfidence10": 3271.797,
    "dayahead11hconfidence90": 5108.703,
    "dayaheadforecast": 4249.495,
    "dayaheadconfidence10": 3271.598,
    "dayaheadconfidence90": 5091.523,
    "weekaheadforecast": 2942.492,
    "weekaheadconfidence10": 1736.17,
    "weekaheadconfidence90": 3753.363,
    "monitoredcapacity": 7428.931,
    "loadfactor": 54.829
  },
  {
    "datetime": "2023-04-13T11:00:00+00:00",
    "resolutioncode": "PT15M",
    "region": "Belgium",
    "measured": 4224.286,
    "mostrecentforecast": 3947.637,
    "mostrecentconfidence10": 2631.216,
    "mostrecentconfidence90": 4588.379,
    "dayahead11hforecast": 4395.718,
    "dayahead11hconfidence10": 3315.564,
    "dayahead11hconfidence90": 5204.949,
    "dayaheadforecast": 4327.907,
    "dayaheadconfidence10": 3366.688,
    "dayaheadconfidence90": 5161.005,
    "weekaheadforecast": 3000.369,
    "weekaheadconfidence10": 1731.815,
    "weekaheadconfidence90": 3793.959,
    "monitoredcapacity": 7428.931,
    "loadfactor": 56.863
  },
  {
    "datetime": "2023-04-13T11:15:00+00:00",
    "resolutioncode": "PT15M",
    "region": "Belgium",
    "measured": 4250.51,
    "mostrecentforecast": 4047.787,
    "mostrecentconfidence10": 2702.391,
    "mostrecentconfidence90": 4723.834,
    "dayahead11hforecast": 4435.539,
    "dayahead11hconfidence10": 3345.706,
    "dayahead11hconfidence90": 5287.055,
    "dayaheadforecast": 4389.315,
    "dayaheadconfidence10": 3400.819,
    "dayaheadconfidence90": 5232.105,
    "weekaheadforecast": 3046.709,
    "weekaheadconfidence10": 1711.993,
    "weekaheadconfidence90": 3870.257,
    "monitoredcapacity": 7428.931,
    "loadfactor": 57.216
  },
  {
    "datetime": "2023-04-13T11:30:00+00:00",
    "resolutioncode": "PT15M",
    "region": "Belgium",
    "measured": 4542.42,
    "mostrecentforecast": 4121.39,
    "mostrecentconfidence10": 2819.653,
    "mostrecentconfidence90": 4821.496,
    "dayahead11hforecast": 4463.487,
    "dayahead11hconfidence10": 3375.342,
    "dayahead11hconfidence90": 5343.745,
    "dayaheadforecast": 4440.866,
    "dayaheadconfidence10": 3420.401,
    "dayaheadconfidence90": 5284.984,
    "weekaheadforecast": 3087.397,
    "weekaheadconfidence10": 1727.898,
    "weekaheadconfidence90": 3900.572,
    "monitoredcapacity": 7428.931,
    "loadfactor": 61.145
  },
  {
    "datetime": "2023-04-13T11:45:00+00:00",
    "resolutioncode": "PT15M",
    "region": "Belgium",
    "measured": 4599.317,
    "mostrecentforecast": 4165.215,
    "mostrecentconfidence10": 2980.382,
    "mostrecentconfidence90": 4862.813,
    "dayahead11hforecast": 4475.335,
    "dayahead11hconfidence10": 3402.329,
    "dayahead11hconfidence90": 5376.279,
    "dayaheadforecast": 4473.753,
    "dayaheadconfidence10": 3442.896,
    "dayaheadconfidence90": 5308.043,
    "weekaheadforecast": 3123.561,
    "weekaheadconfidence10": 1759.333,
    "weekaheadconfidence90": 3884.471,
    "monitoredcapacity": 7428.931,
    "loadfactor": 61.911
  },
  {
    "datetime": "2023-04-13T12:00:00+00:00",
    "resolutioncode": "PT15M",
    "region": "Belgium",
    "measured": 4494.561,
    "mostrecentforecast": 4336.845,
    "mostrecentconfidence10": 3241.446,
    "mostrecentconfidence90": 5018.101,
    "dayahead11hforecast": 4463.716,
    "dayahead11hconfidence10": 3404.191,
    "dayahead11hconfidence90": 5394.219,
    "dayaheadforecast": 4483.685,
    "dayaheadconfidence10": 3435.43,
    "dayaheadconfidence90": 5322.231,
    "weekaheadforecast": 3147.731,
    "weekaheadconfidence10": 1764.081,
    "weekaheadconfidence90": 3929.978,
    "monitoredcapacity": 7428.931,
    "loadfactor": 60.501
  },
  {
    "datetime": "2023-04-13T12:15:00+00:00",
    "resolutioncode": "PT15M",
    "region": "Belgium",
    "measured": 4703.208,
    "mostrecentforecast": 4337.695,
    "mostrecentconfidence10": 3313.501,
    "mostrecentconfidence90": 5039.935,
    "dayahead11hforecast": 4429.118,
    "dayahead11hconfidence10": 3376.431,
    "dayahead11hconfidence90": 5410.352,
    "dayaheadforecast": 4473.029,
    "dayaheadconfidence10": 3408.652,
    "dayaheadconfidence90": 5333.648,
    "weekaheadforecast": 3157.678,
    "weekaheadconfidence10": 1729.885,
    "weekaheadconfidence90": 4012.745,
    "monitoredcapacity": 7428.931,
    "loadfactor": 63.309
  },
  {
    "datetime": "2023-04-13T12:30:00+00:00",
    "resolutioncode": "PT15M",
    "region": "Belgium",
    "measured": 4547.197,
    "mostrecentforecast": 4314.445,
    "mostrecentconfidence10": 3330.288,
    "mostrecentconfidence90": 5021.141,
    "dayahead11hforecast": 4379.484,
    "dayahead11hconfidence10": 3340.084,
    "dayahead11hconfidence90": 5401.076,
    "dayaheadforecast": 4441.151,
    "dayaheadconfidence10": 3365.476,
    "dayaheadconfidence90": 5313.357,
    "weekaheadforecast": 3147.071,
    "weekaheadconfidence10": 1694.365,
    "weekaheadconfidence90": 4021.017,
    "monitoredcapacity": 7428.931,
    "loadfactor": 61.209
  },
  {
    "datetime": "2023-04-13T12:45:00+00:00",
    "resolutioncode": "PT15M",
    "region": "Belgium",
    "measured": 4380.078,
    "mostrecentforecast": 4266.859,
    "mostrecentconfidence10": 3314.704,
    "mostrecentconfidence90": 4951.978,
    "dayahead11hforecast": 4307.948,
    "dayahead11hconfidence10": 3283.058,
    "dayahead11hconfidence90": 5366.319,
    "dayaheadforecast": 4385.172,
    "dayaheadconfidence10": 3310.617,
    "dayaheadconfidence90": 5259.621,
    "weekaheadforecast": 3116.069,
    "weekaheadconfidence10": 1652.785,
    "weekaheadconfidence90": 3960.024,
    "monitoredcapacity": 7428.931,
    "loadfactor": 58.96
  },
  {
    "datetime": "2023-04-13T13:00:00+00:00",
    "resolutioncode": "PT15M",
    "region": "Belgium",
    "measured": 4426.787,
    "mostrecentforecast": 4221.122,
    "mostrecentconfidence10": 3261.926,
    "mostrecentconfidence90": 4880.625,
    "dayahead11hforecast": 4207.084,
    "dayahead11hconfidence10": 3174.082,
    "dayahead11hconfidence90": 5315.224,
    "dayaheadforecast": 4299.739,
    "dayaheadconfidence10": 3238.983,
    "dayaheadconfidence90": 5171.053,
    "weekaheadforecast": 3069.115,
    "weekaheadconfidence10": 1593.664,
    "weekaheadconfidence90": 3911.247,
    "monitoredcapacity": 7428.931,
    "loadfactor": 59.588
  },
  {
    "datetime": "2023-04-13T13:15:00+00:00",
    "resolutioncode": "PT15M",
    "region": "Belgium",
    "measured": 4188.562,
    "mostrecentforecast": 4127.333,
    "mostrecentconfidence10": 3177.826,
    "mostrecentconfidence90": 4787.932,
    "dayahead11hforecast": 4087.797,
    "dayahead11hconfidence10": 3038.441,
    "dayahead11hconfidence90": 5244.555,
    "dayaheadforecast": 4187.667,
    "dayaheadconfidence10": 3145.011,
    "dayaheadconfidence90": 5057.139,
    "weekaheadforecast": 3004.647,
    "weekaheadconfidence10": 1521.782,
    "weekaheadconfidence90": 3860.191,
    "monitoredcapacity": 7428.931,
    "loadfactor": 56.382
  },
  {
    "datetime": "2023-04-13T13:30:00+00:00",
    "resolutioncode": "PT15M",
    "region": "Belgium",
    "measured": 4174.704,
    "mostrecentforecast": 4021.392,
    "mostrecentconfidence10": 3100.863,
    "mostrecentconfidence90": 4654.891,
    "dayahead11hforecast": 3976.914,
    "dayahead11hconfidence10": 2958.721,
    "dayahead11hconfidence90": 5131.722,
    "dayaheadforecast": 4064.536,
    "dayaheadconfidence10": 3055.703,
    "dayaheadconfidence90": 4868.493,
    "weekaheadforecast": 2928.494,
    "weekaheadconfidence10": 1471.237,
    "weekaheadconfidence90": 3780.264,
    "monitoredcapacity": 7428.931,
    "loadfactor": 56.195
  },
  {
    "datetime": "2023-04-13T13:45:00+00:00",
    "resolutioncode": "PT15M",
    "region": "Belgium",
    "measured": 4144.553,
    "mostrecentforecast": 3895.935,
    "mostrecentconfidence10": 3037.691,
    "mostrecentconfidence90": 4487.65,
    "dayahead11hforecast": 3869.873,
    "dayahead11hconfidence10": 2938.719,
    "dayahead11hconfidence90": 4944.924,
    "dayaheadforecast": 3927.673,
    "dayaheadconfidence10": 2984.704,
    "dayaheadconfidence90": 4649.979,
    "weekaheadforecast": 2840.969,
    "weekaheadconfidence10": 1443.16,
    "weekaheadconfidence90": 3681.106,
    "monitoredcapacity": 7428.931,
    "loadfactor": 55.789
  },
  {
    "datetime": "2023-04-13T14:00:00+00:00",
    "resolutioncode": "PT15M",
    "region": "Belgium",
    "measured": 3930.448,
    "mostrecentforecast": 3754.317,
    "mostrecentconfidence10": 2948.283,
    "mostrecentconfidence90": 4356.722,
    "dayahead11hforecast": 3738.342,
    "dayahead11hconfidence10": 2871.848,
    "dayahead11hconfidence90": 4693.682,
    "dayaheadforecast": 3769.615,
    "dayaheadconfidence10": 2890.047,
    "dayaheadconfidence90": 4463.393,
    "weekaheadforecast": 2734.176,
    "weekaheadconfidence10": 1393.451,
    "weekaheadconfidence90": 3569.696,
    "monitoredcapacity": 7428.931,
    "loadfactor": 52.907
  },
  {
    "datetime": "2023-04-13T14:15:00+00:00",
    "resolutioncode": "PT15M",
    "region": "Belgium",
    "measured": 3773.966,
    "mostrecentforecast": 3561.069,
    "mostrecentconfidence10": 2792.46,
    "mostrecentconfidence90": 4169.066,
    "dayahead11hforecast": 3575.821,
    "dayahead11hconfidence10": 2733.63,
    "dayahead11hconfidence90": 4426.091,
    "dayaheadforecast": 3591.108,
    "dayaheadconfidence10": 2734.809,
    "dayaheadconfidence90": 4267.208,
    "weekaheadforecast": 2607.425,
    "weekaheadconfidence10": 1333.438,
    "weekaheadconfidence90": 3444.517,
    "monitoredcapacity": 7428.931,
    "loadfactor": 50.801
  },
  {
    "datetime": "2023-04-13T14:30:00+00:00",
    "resolutioncode": "PT15M",
    "region": "Belgium",
    "measured": 3496.342,
    "mostrecentforecast": 3357.775,
    "mostrecentconfidence10": 2631.737,
    "mostrecentconfidence90": 3942.254,
    "dayahead11hforecast": 3389.417,
    "dayahead11hconfidence10": 2597.791,
    "dayahead11hconfidence90": 4113.849,
    "dayaheadforecast": 3399.298,
    "dayaheadconfidence10": 2571.728,
    "dayaheadconfidence90": 4026.225,
    "weekaheadforecast": 2463.878,
    "weekaheadconfidence10": 1269.498,
    "weekaheadconfidence90": 3280.265,
    "monitoredcapacity": 7428.931,
    "loadfactor": 47.064
  },
  {
    "datetime": "2023-04-13T14:45:00+00:00",
    "resolutioncode": "PT15M",
    "region": "Belgium",
    "measured": 3356.133,
    "mostrecentforecast": 3151.223,
    "mostrecentconfidence10": 2462.069,
    "mostrecentconfidence90": 3687.69,
    "dayahead11hforecast": 3185.11,
    "dayahead11hconfidence10": 2458.116,
    "dayahead11hconfidence90": 3758.34,
    "dayaheadforecast": 3192.753,
    "dayaheadconfidence10": 2408.507,
    "dayaheadconfidence90": 3744.065,
    "weekaheadforecast": 2305.486,
    "weekaheadconfidence10": 1201.889,
    "weekaheadconfidence90": 3086.098,
    "monitoredcapacity": 7428.931,
    "loadfactor": 45.177
  },
  {
    "datetime": "2023-04-13T15:00:00+00:00",
    "resolutioncode": "PT15M",
    "region": "Belgium",
    "measured": 3048.842,
    "mostrecentforecast": 3026.339,
    "mostrecentconfidence10": 2345.212,
    "mostrecentconfidence90": 3532.754,
    "dayahead11hforecast": 2964.959,
    "dayahead11hconfidence10": 2254.011,
    "dayahead11hconfidence90": 3444.743,
    "dayaheadforecast": 2966.682,
    "dayaheadconfidence10": 2179.436,
    "dayaheadconfidence90": 3452.638,
    "weekaheadforecast": 2127.647,
    "weekaheadconfidence10": 1127.862,
    "weekaheadconfidence90": 2869.148,
    "monitoredcapacity": 7428.931,
    "loadfactor": 41.04
  },
  {
    "datetime": "2023-04-13T15:15:00+00:00",
    "resolutioncode": "PT15M",
    "region": "Belgium",
    "measured": 2642.563,
    "mostrecentforecast": 2761.724,
    "mostrecentconfidence10": 2053.143,
    "mostrecentconfidence90": 3267.773,
    "dayahead11hforecast": 2731.27,
    "dayahead11hconfidence10": 1992.265,
    "dayahead11hconfidence90": 3172.806,
    "dayaheadforecast": 2728.636,
    "dayaheadconfidence10": 1906.932,
    "dayaheadconfidence90": 3169.649,
    "weekaheadforecast": 1929.685,
    "weekaheadconfidence10": 1050.362,
    "weekaheadconfidence90": 2616.275,
    "monitoredcapacity": 7428.931,
    "loadfactor": 35.571
  },
  {
    "datetime": "2023-04-13T15:30:00+00:00",
    "resolutioncode": "PT15M",
    "region": "Belgium",
    "measured": 2329.35,
    "mostrecentforecast": 2491.155,
    "mostrecentconfidence10": 1805.07,
    "mostrecentconfidence90": 3001.475,
    "dayahead11hforecast": 2486.561,
    "dayahead11hconfidence10": 1740.891,
    "dayahead11hconfidence90": 2913.408,
    "dayaheadforecast": 2482.094,
    "dayaheadconfidence10": 1687.906,
    "dayaheadconfidence90": 2891.696,
    "weekaheadforecast": 1722.161,
    "weekaheadconfidence10": 969.906,
    "weekaheadconfidence90": 2353.409,
    "monitoredcapacity": 7428.931,
    "loadfactor": 31.355
  },
  {
    "datetime": "2023-04-13T15:45:00+00:00",
    "resolutioncode": "PT15M",
    "region": "Belgium",
    "measured": 1946.687,
    "mostrecentforecast": 2206.858,
    "mostrecentconfidence10": 1606.969,
    "mostrecentconfidence90": 2677.477,
    "dayahead11hforecast": 2218.538,
    "dayahead11hconfidence10": 1505.099,
    "dayahead11hconfidence90": 2641.755,
    "dayaheadforecast": 2207.625,
    "dayaheadconfidence10": 1518.692,
    "dayaheadconfidence90": 2597.457,
    "weekaheadforecast": 1509.286,
    "weekaheadconfidence10": 884.46,
    "weekaheadconfidence90": 2076.494,
    "monitoredcapacity": 7428.931,
    "loadfactor": 26.204
  },
  {
    "datetime": "2023-04-13T16:00:00+00:00",
    "resolutioncode": "PT15M",
    "region": "Belgium",
    "measured": 1672.219,
    "mostrecentforecast": 1846.846,
    "mostrecentconfidence10": 1342.434,
    "mostrecentconfidence90": 2280.24,
    "dayahead11hforecast": 1908.872,
    "dayahead11hconfidence10": 1279.141,
    "dayahead11hconfidence90": 2349.438,
    "dayaheadforecast": 1891.619,
    "dayaheadconfidence10": 1312.548,
    "dayaheadconfidence90": 2271.153,
    "weekaheadforecast": 1291.817,
    "weekaheadconfidence10": 794.908,
    "weekaheadconfidence90": 1768.234,
    "monitoredcapacity": 7428.931,
    "loadfactor": 22.51
  },
  {
    "datetime": "2023-04-13T16:15:00+00:00",
    "resolutioncode": "PT15M",
    "region": "Belgium",
    "measured": 1473.049,
    "mostrecentforecast": 1521.024,
    "mostrecentconfidence10": 1139.986,
    "mostrecentconfidence90": 1896.249,
    "dayahead11hforecast": 1580.545,
    "dayahead11hconfidence10": 1073.048,
    "dayahead11hconfidence90": 2036.221,
    "dayaheadforecast": 1560.929,
    "dayaheadconfidence10": 1102.196,
    "dayaheadconfidence90": 1917.469,
    "weekaheadforecast": 1077.76,
    "weekaheadconfidence10": 703.255,
    "weekaheadconfidence90": 1453.629,
    "monitoredcapacity": 7428.931,
    "loadfactor": 19.829
  },
  {
    "datetime": "2023-04-13T16:30:00+00:00",
    "resolutioncode": "PT15M",
    "region": "Belgium",
    "measured": 1175.991,
    "mostrecentforecast": 1225.781,
    "mostrecentconfidence10": 947.917,
    "mostrecentconfidence90": 1517.865,
    "dayahead11hforecast": 1264.235,
    "dayahead11hconfidence10": 878.205,
    "dayahead11hconfidence90": 1662.409,
    "dayaheadforecast": 1246.11,
    "dayaheadconfidence10": 900.59,
    "dayaheadconfidence90": 1536.392,
    "weekaheadforecast": 873.346,
    "weekaheadconfidence10": 609.165,
    "weekaheadconfidence90": 1142.725,
    "monitoredcapacity": 7428.931,
    "loadfactor": 15.83
  },
  {
    "datetime": "2023-04-13T16:45:00+00:00",
    "resolutioncode": "PT15M",
    "region": "Belgium",
    "measured": 842.952,
    "mostrecentforecast": 968.168,
    "mostrecentconfidence10": 773.66,
    "mostrecentconfidence90": 1186.879,
    "dayahead11hforecast": 980.119,
    "dayahead11hconfidence10": 694.443,
    "dayahead11hconfidence90": 1270.958,
    "dayaheadforecast": 966.067,
    "dayaheadconfidence10": 709.246,
    "dayaheadconfidence90": 1194.746,
    "weekaheadforecast": 683.757,
    "weekaheadconfidence10": 515.089,
    "weekaheadconfidence90": 846.256,
    "monitoredcapacity": 7428.931,
    "loadfactor": 11.347
  },
  {
    "datetime": "2023-04-13T17:00:00+00:00",
    "resolutioncode": "PT15M",
    "region": "Belgium",
    "measured": 699.075,
    "mostrecentforecast": 704.812,
    "mostrecentconfidence10": 580.229,
    "mostrecentconfidence90": 912.508,
    "dayahead11hforecast": 722.079,
    "dayahead11hconfidence10": 522.6,
    "dayahead11hconfidence90": 970.35,
    "dayaheadforecast": 713.216,
    "dayaheadconfidence10": 530.12,
    "dayaheadconfidence90": 938.512,
    "weekaheadforecast": 511.569,
    "weekaheadconfidence10": 420.578,
    "weekaheadconfidence90": 594.409,
    "monitoredcapacity": 7428.931,
    "loadfactor": 9.41
  },
  {
    "datetime": "2023-04-13T17:15:00+00:00",
    "resolutioncode": "PT15M",
    "region": "Belgium",
    "measured": 489.78,
    "mostrecentforecast": 481.209,
    "mostrecentconfidence10": 400.331,
    "mostrecentconfidence90": 686.628,
    "dayahead11hforecast": 486.893,
    "dayahead11hconfidence10": 363.626,
    "dayahead11hconfidence90": 715.37,
    "dayaheadforecast": 482.817,
    "dayaheadconfidence10": 366.587,
    "dayaheadconfidence90": 705.565,
    "weekaheadforecast": 359.791,
    "weekaheadconfidence10": 309.729,
    "weekaheadconfidence90": 421.897,
    "monitoredcapacity": 7428.931,
    "loadfactor": 6.593
  },
  {
    "datetime": "2023-04-13T17:30:00+00:00",
    "resolutioncode": "PT15M",
    "region": "Belgium",
    "measured": 305.235,
    "mostrecentforecast": 291.947,
    "mostrecentconfidence10": 229.42,
    "mostrecentconfidence90": 483.736,
    "dayahead11hforecast": 294.206,
    "dayahead11hconfidence10": 223.282,
    "dayahead11hconfidence90": 493.631,
    "dayaheadforecast": 293.493,
    "dayaheadconfidence10": 222.71,
    "dayaheadconfidence90": 496.21,
    "weekaheadforecast": 240.605,
    "weekaheadconfidence10": 188.748,
    "weekaheadconfidence90": 286.355,
    "monitoredcapacity": 7428.931,
    "loadfactor": 4.109
  },
  {
    "datetime": "2023-04-13T17:45:00+00:00",
    "resolutioncode": "PT15M",
    "region": "Belgium",
    "measured": 171.883,
    "mostrecentforecast": 169.997,
    "mostrecentconfidence10": 118.975,
    "mostrecentconfidence90": 313.994,
    "dayahead11hforecast": 170.579,
    "dayahead11hconfidence10": 125.403,
    "dayahead11hconfidence90": 317.529,
    "dayaheadforecast": 170.71,
    "dayaheadconfidence10": 125.522,
    "dayaheadconfidence90": 319.755,
    "weekaheadforecast": 153.465,
    "weekaheadconfidence10": 113.381,
    "weekaheadconfidence90": 178.397,
    "monitoredcapacity": 7428.931,
    "loadfactor": 2.314
  },
  {
    "datetime": "2023-04-13T18:00:00+00:00",
    "resolutioncode": "PT15M",
    "region": "Belgium",
    "measured": 85.573,
    "mostrecentforecast": 93.949,
    "mostrecentconfidence10": 66.956,
    "mostrecentconfidence90": 179.712,
    "dayahead11hforecast": 94.699,
    "dayahead11hconfidence10": 63.73,
    "dayahead11hconfidence90": 184.072,
    "dayaheadforecast": 94.857,
    "dayaheadconfidence10": 63.822,
    "dayaheadconfidence90": 185.478,
    "weekaheadforecast": 84.33,
    "weekaheadconfidence10": 64.068,
    "weekaheadconfidence90": 96.407,
    "monitoredcapacity": 7428.931,
    "loadfactor": 1.152
  },
  {
    "datetime": "2023-04-13T18:15:00+00:00",
    "resolutioncode": "PT15M",
    "region": "Belgium",
    "measured": 31.746,
    "mostrecentforecast": 32.659,
    "mostrecentconfidence10": 23.534,
    "mostrecentconfidence90": 63.556,
    "dayahead11hforecast": 32.8,
    "dayahead11hconfidence10": 20.608,
    "dayahead11hconfidence90": 66.742,
    "dayaheadforecast": 32.969,
    "dayaheadconfidence10": 20.732,
    "dayaheadconfidence90": 66.124,
    "weekaheadforecast": 27.471,
    "weekaheadconfidence10": 20.034,
    "weekaheadconfidence90": 31.266,
    "monitoredcapacity": 7428.931,
    "loadfactor": 0.427
  },
  {
    "datetime": "2023-04-13T18:30:00+00:00",
    "resolutioncode": "PT15M",
    "region": "Belgium",
    "measured": 2.332,
    "mostrecentforecast": 1.945,
    "mostrecentconfidence10": 1.508,
    "mostrecentconfidence90": 3.869,
    "dayahead11hforecast": 1.888,
    "dayahead11hconfidence10": 1.203,
    "dayahead11hconfidence90": 4.029,
    "dayaheadforecast": 1.955,
    "dayaheadconfidence10": 1.229,
    "dayaheadconfidence90": 3.973,
    "weekaheadforecast": 1.535,
    "weekaheadconfidence10": 1.015,
    "weekaheadconfidence90": 1.886,
    "monitoredcapacity": 7428.931,
    "loadfactor": 0.031
  },
  {
    "datetime": "2023-04-13T18:45:00+00:00",
    "resolutioncode": "PT15M",
    "region": "Belgium",
    "measured": 0.079,
    "mostrecentforecast": 0.0,
    "mostrecentconfidence10": 0.0,
    "mostrecentconfidence90": 0.0,
    "dayahead11hforecast": 0.0,
    "dayahead11hconfidence10": 0.0,
    "dayahead11hconfidence90": 0.0,
    "dayaheadforecast": 0.0,
    "dayaheadconfidence10": 0.0,
    "dayaheadconfidence90": 0.0,
    "weekaheadforecast": 0.0,
    "weekaheadconfidence10": 0.0,
    "weekaheadconfidence90": 0.0,
    "monitoredcapacity": 7428.931,
    "loadfactor": 0.001
  },
  {
    "datetime": "2023-04-13T19:00:00+00:00",
    "resolutioncode": "PT15M",
    "region": "Belgium",
    "measured": 0.0,
    "mostrecentforecast": 0.0,
    "mostrecentconfidence10": 0.0,
    "mostrecentconfidence90": 0.0,
    "dayahead11hforecast": 0.0,
    "dayahead11hconfidence10": 0.0,
    "dayahead11hconfidence90": 0.0,
    "dayaheadforecast": 0.0,
    "dayaheadconfidence10": 0.0,
    "dayaheadconfidence90": 0.0,
    "weekaheadforecast": 0.0,
    "weekaheadconfidence10": 0.0,
    "weekaheadconfidence90": 0.0,
    "monitoredcapacity": 7428.931,
    "loadfactor": 0.0
  },
  {
    "datetime": "2023-04-13T19:15:00+00:00",
    "resolutioncode": "PT15M",
    "region": "Belgium",
    "measured": 0.0,
    "mostrecentforecast": 0.0,
    "mostrecentconfidence10": 0.0,
    "mostrecentconfidence90": 0.0,
    "dayahead11hforecast": 0.0,
    "dayahead11hconfidence10": 0.0,
    "dayahead11hconfidence90": 0.0,
    "dayaheadforecast": 0.0,
    "dayaheadconfidence10": 0.0,
    "dayaheadconfidence90": 0.0,
    "weekaheadforecast": 0.0,
    "weekaheadconfidence10": 0.0,
    "weekaheadconfidence90": 0.0,
    "monitoredcapacity": 7428.931,
    "loadfactor": 0.0
  },
  {
    "datetime": "2023-04-13T19:30:00+00:00",
    "resolutioncode": "PT15M",
    "region": "Belgium",
    "measured": 0.0,
    "mostrecentforecast": 0.0,
    "mostrecentconfidence10": 0.0,
    "mostrecentconfidence90": 0.0,
    "dayahead11hforecast": 0.0,
    "dayahead11hconfidence10": 0.0,
    "dayahead11hconfidence90": 0.0,
    "dayaheadforecast": 0.0,
    "dayaheadconfidence10": 0.0,
    "dayaheadconfidence90": 0.0,
    "weekaheadforecast": 0.0,
    "weekaheadconfidence10": 0.0,
    "weekaheadconfidence90": 0.0,
    "monitoredcapacity": 7428.931,
    "loadfactor": 0.0
  },
  {
    "datetime": "2023-04-13T19:45:00+00:00",
    "resolutioncode": "PT15M",
    "region": "Belgium",
    "measured": 0.0,
    "mostrecentforecast": 0.0,
    "mostrecentconfidence10": 0.0,
    "mostrecentconfidence90": 0.0,
    "dayahead11hforecast": 0.0,
    "dayahead11hconfidence10": 0.0,
    "dayahead11hconfidence90": 0.0,
    "dayaheadforecast": 0.0,
    "dayaheadconfidence10": 0.0,
    "dayaheadconfidence90": 0.0,
    "weekaheadforecast": 0.0,
    "weekaheadconfidence10": 0.0,
    "weekaheadconfidence90": 0.0,
    "monitoredcapacity": 7428.931,
    "loadfactor": 0.0
  },
  {
    "datetime": "2023-04-13T20:00:00+00:00",
    "resolutioncode": "PT15M",
    "region": "Belgium",
    "measured": 0.0,
    "mostrecentforecast": 0.0,
    "mostrecentconfidence10": 0.0,
    "mostrecentconfidence90": 0.0,
    "dayahead11hforecast": 0.0,
    "dayahead11hconfidence10": 0.0,
    "dayahead11hconfidence90": 0.0,
    "dayaheadforecast": 0.0,
    "dayaheadconfidence10": 0.0,
    "dayaheadconfidence90": 0.0,
    "weekaheadforecast": 0.0,
    "weekaheadconfidence10": 0.0,
    "weekaheadconfidence90": 0.0,
    "monitoredcapacity": 7428.931,
    "loadfactor": 0.0
  },
  {
    "datetime": "2023-04-13T20:15:00+00:00",
    "resolutioncode": "PT15M",
    "region": "Belgium",
    "measured": 0.0,
    "mostrecentforecast": 0.0,
    "mostrecentconfidence10": 0.0,
    "mostrecentconfidence90": 0.0,
    "dayahead11hforecast": 0.0,
    "dayahead11hconfidence10": 0.0,
    "dayahead11hconfidence90": 0.0,
    "dayaheadforecast": 0.0,
    "dayaheadconfidence10": 0.0,
    "dayaheadconfidence90": 0.0,
    "weekaheadforecast": 0.0,
    "weekaheadconfidence10": 0.0,
    "weekaheadconfidence90": 0.0,
    "monitoredcapacity": 7428.931,
    "loadfactor": 0.0
  },
  {
    "datetime": "2023-04-13T20:30:00+00:00",
    "resolutioncode": "PT15M",
    "region": "Belgium",
    "measured": 0.0,
    "mostrecentforecast": 0.0,
    "mostrecentconfidence10": 0.0,
    "mostrecentconfidence90": 0.0,
    "dayahead11hforecast": 0.0,
    "dayahead11hconfidence10": 0.0,
    "dayahead11hconfidence90": 0.0,
    "dayaheadforecast": 0.0,
    "dayaheadconfidence10": 0.0,
    "dayaheadconfidence90": 0.0,
    "weekaheadforecast": 0.0,
    "weekaheadconfidence10": 0.0,
    "weekaheadconfidence90": 0.0,
    "monitoredcapacity": 7428.931,
    "loadfactor": 0.0
  },
  {
    "datetime": "2023-04-13T20:45:00+00:00",
    "resolutioncode": "PT15M",
    "region": "Belgium",
    "measured": 0.0,
    "mostrecentforecast": 0.0,
    "mostrecentconfidence10": 0.0,
    "mostrecentconfidence90": 0.0,
    "dayahead11hforecast": 0.0,
    "dayahead11hconfidence10": 0.0,
    "dayahead11hconfidence90": 0.0,
    "dayaheadforecast": 0.0,
    "dayaheadconfidence10": 0.0,
    "dayaheadconfidence90": 0.0,
    "weekaheadforecast": 0.0,
    "weekaheadconfidence10": 0.0,
    "weekaheadconfidence90": 0.0,
    "monitoredcapacity": 7428.931,
    "loadfactor": 0.0
  },
  {
    "datetime": "2023-04-13T21:00:00+00:00",
    "resolutioncode": "PT15M",
    "region": "Belgium",
    "measured": 0.0,
    "mostrecentforecast": 0.0,
    "mostrecentconfidence10": 0.0,
    "mostrecentconfidence90": 0.0,
    "dayahead11hforecast": 0.0,
    "dayahead11hconfidence10": 0.0,
    "dayahead11hconfidence90": 0.0,
    "dayaheadforecast": 0.0,
    "dayaheadconfidence10": 0.0,
    "dayaheadconfidence90": 0.0,
    "weekaheadforecast": 0.0,
    "weekaheadconfidence10": 0.0,
    "weekaheadconfidence90": 0.0,
    "monitoredcapacity": 7428.931,
    "loadfactor": 0.0
  },
  {
    "datetime": "2023-04-13T21:15:00+00:00",
    "resolutioncode": "PT15M",
    "region": "Belgium",
    "measured": 0.0,
    "mostrecentforecast": 0.0,
    "mostrecentconfidence10": 0.0,
    "mostrecentconfidence90": 0.0,
    "dayahead11hforecast": 0.0,
    "dayahead11hconfidence10": 0.0,
    "dayahead11hconfidence90": 0.0,
    "dayaheadforecast": 0.0,
    "dayaheadconfidence10": 0.0,
    "dayaheadconfidence90": 0.0,
    "weekaheadforecast": 0.0,
    "weekaheadconfidence10": 0.0,
    "weekaheadconfidence90": 0.0,
    "monitoredcapacity": 7428.931,
    "loadfactor": 0.0
  },
  {
    "datetime": "2023-04-13T21:30:00+00:00",
    "resolutioncode": "PT15M",
    "region": "Belgium",
    "measured": 0.0,
    "mostrecentforecast": 0.0,
    "mostrecentconfidence10": 0.0,
    "mostrecentconfidence90": 0.0,
    "dayahead11hforecast": 0.0,
    "dayahead11hconfidence10": 0.0,
    "dayahead11hconfidence90": 0.0,
    "dayaheadforecast": 0.0,
    "dayaheadconfidence10": 0.0,
    "dayaheadconfidence90": 0.0,
    "weekaheadforecast": 0.0,
    "weekaheadconfidence10": 0.0,
    "weekaheadconfidence90": 0.0,
    "monitoredcapacity": 7428.931,
    "loadfactor": 0.0
  },
  {
    "datetime": "2023-04-13T21:45:00+00:00",
    "resolutioncode": "PT15M",
    "region": "Belgium",
    "measured": null,
    "mostrecentforecast": 0.0,
    "mostrecentconfidence10": 0.0,
    "mostrecentconfidence90": 0.0,
    "dayahead11hforecast": 0.0,
    "dayahead11hconfidence10": 0.0,
    "dayahead11hconfidence90": 0.0,
    "dayaheadforecast": 0.0,
    "dayaheadconfidence10": 0.0,
    "dayaheadconfidence90": 0.0,
    "weekaheadforecast": 0.0,
    "weekaheadconfidence10": 0.0,
    "weekaheadconfidence90": 0.0,
    "monitoredcapacity": 7428.931,
    "loadfactor": null
  },
  {
    "datetime": "2023-04-13T22:00:00+00:00",
    "resolutioncode": "PT15M",
    "region": "Belgium",
    "measured": 0.0,
    "mostrecentforecast": 0.0,
    "mostrecentconfidence10": 0.0,
    "mostrecentconfidence90": 0.0,
    "dayahead11hforecast": 0.0,
    "dayahead11hconfidence10": 0.0,
    "dayahead11hconfidence90": 0.0,
    "dayaheadforecast": 0.0,
    "dayaheadconfidence10": 0.0,
    "dayaheadconfidence90": 0.0,
    "weekaheadforecast": 0.0,
    "weekaheadconfidence10": 0.0,
    "weekaheadconfidence90": 0.0,
    "monitoredcapacity": 7428.931,
    "loadfactor": 0.0
  },
  {
    "datetime": "2023-04-13T22:15:00+00:00",
    "resolutioncode": "PT15M",
    "region": "Belgium",
    "measured": 0.0,
    "mostrecentforecast": 0.0,
    "mostrecentconfidence10": 0.0,
    "mostrecentconfidence90": 0.0,
    "dayahead11hforecast": 0.0,
    "dayahead11hconfidence10": 0.0,
    "dayahead11hconfidence90": 0.0,
    "dayaheadforecast": 0.0,
    "dayaheadconfidence10": 0.0,
    "dayaheadconfidence90": 0.0,
    "weekaheadforecast": 0.0,
    "weekaheadconfidence10": 0.0,
    "weekaheadconfidence90": 0.0,
    "monitoredcapacity": 7428.931,
    "loadfactor": 0.0
  },
  {
    "datetime": "2023-04-13T22:30:00+00:00",
    "resolutioncode": "PT15M",
    "region": "Belgium",
    "measured": 0.0,
    "mostrecentforecast": 0.0,
    "mostrecentconfidence10": 0.0,
    "mostrecentconfidence90": 0.0,
    "dayahead11hforecast": 0.0,
    "dayahead11hconfidence10": 0.0,
    "dayahead11hconfidence90": 0.0,
    "dayaheadforecast": 0.0,
    "dayaheadconfidence10": 0.0,
    "dayaheadconfidence90": 0.0,
    "weekaheadforecast": 0.0,
    "weekaheadconfidence10": 0.0,
    "weekaheadconfidence90": 0.0,
    "monitoredcapacity": 7428.931,
    "loadfactor": 0.0
  },
  {
    "datetime": "2023-04-13T22:45:00+00:00",
    "resolutioncode": "PT15M",
    "region": "Belgium",
    "measured": 0.0,
    "mostrecentforecast": 0.0,
    "mostrecentconfidence10": 0.0,
    "mostrecentconfidence90": 0.0,
    "dayahead11hforecast": 0.0,
    "dayahead11hconfidence10": 0.0,
    "dayahead11hconfidence90": 0.0,
    "dayaheadforecast": 0.0,
    "dayaheadconfidence10": 0.0,
    "dayaheadconfidence90": 0.0,
    "weekaheadforecast": 0.0,
    "weekaheadconfidence10": 0.0,
    "weekaheadconfidence90": 0.0,
    "monitoredcapacity": 7428.931,
    "loadfactor": 0.0
  },
  {
    "datetime": "2023-04-13T23:00:00+00:00",
    "resolutioncode": "PT15M",
    "region": "Belgium",
    "measured": 0.0,
    "mostrecentforecast": 0.0,
    "mostrecentconfidence10": 0.0,
    "mostrecentconfidence90": 0.0,
    "dayahead11hforecast": 0.0,
    "dayahead11hconfidence10": 0.0,
    "dayahead11hconfidence90": 0.0,
    "dayaheadforecast": 0.0,
    "dayaheadconfidence10": 0.0,
    "dayaheadconfidence90": 0.0,
    "weekaheadforecast": 0.0,
    "weekaheadconfidence10": 0.0,
    "weekaheadconfidence90": 0.0,
    "monitoredcapacity": 7428.931,
    "loadfactor": 0.0
  },
  {
    "datetime": "2023-04-13T23:15:00+00:00",
    "resolutioncode": "PT15M",
    "region": "Belgium",
    "measured": 0.0,
    "mostrecentforecast": 0.0,
    "mostrecentconfidence10": 0.0,
    "mostrecentconfidence90": 0.0,
    "dayahead11hforecast": 0.0,
    "dayahead11hconfidence10": 0.0,
    "dayahead11hconfidence90": 0.0,
    "dayaheadforecast": 0.0,
    "dayaheadconfidence10": 0.0,
    "dayaheadconfidence90": 0.0,
    "weekaheadforecast": 0.0,
    "weekaheadconfidence10": 0.0,
    "weekaheadconfidence90": 0.0,
    "monitoredcapacity": 7428.931,
    "loadfactor": 0.0
  },
  {
    "datetime": "2023-04-13T23:30:00+00:00",
    "resolutioncode": "PT15M",
    "region": "Belgium",
    "measured": 0.0,
    "mostrecentforecast": 0.0,
    "mostrecentconfidence10": 0.0,
    "mostrecentconfidence90": 0.0,
    "dayahead11hforecast": 0.0,
    "dayahead11hconfidence10": 0.0,
    "dayahead11hconfidence90": 0.0,
    "dayaheadforecast": 0.0,
    "dayaheadconfidence10": 0.0,
    "dayaheadconfidence90": 0.0,
    "weekaheadforecast": 0.0,
    "weekaheadconfidence10": 0.0,
    "weekaheadconfidence90": 0.0,
    "monitoredcapacity": 7428.931,
    "loadfactor": 0.0
  },
  {
    "datetime": "2023-04-13T23:45:00+00:00",
    "resolutioncode": "PT15M",
    "region": "Belgium",
    "measured": 0.0,
    "mostrecentforecast": 0.0,
    "mostrecentconfidence10": 0.0,
    "mostrecentconfidence90": 0.0,
    "dayahead11hforecast": 0.0,
    "dayahead11hconfidence10": 0.0,
    "dayahead11hconfidence90": 0.0,
    "dayaheadforecast": 0.0,
    "dayaheadconfidence10": 0.0,
    "dayaheadconfidence90": 0.0,
    "weekaheadforecast": 0.0,
    "weekaheadconfidence10": 0.0,
    "weekaheadconfidence90": 0.0,
    "monitoredcapacity": 7428.931,
    "loadfactor": 0.0
  }
]